{
  "__inputs": [
    {
      "name": "DS_PROMETHEUS",
      "label": "Prometheus",
      "description": "",
      "type": "datasource",
      "pluginId": "prometheus",
      "pluginName": "Prometheus"
    }
  ],
  "__requires": [
    { "type": "grafana", "id": "grafana", "name": "Grafana", "version": "10.0.0" },
    { "type": "datasource", "id": "prometheus", "name": "Prometheus", "version": "1.0.0" },
    { "type": "panel", "id": "timeseries", "name": "Time series", "version": "" },
    { "type": "panel", "id": "gauge", "name": "Gauge", "version": "" },
    { "type": "panel", "id": "stat", "name": "Stat", "version": "" },
    { "type": "panel", "id": "table", "name": "Table", "version": "" }
  ],
  "annotations": {
    "list": [
      {
        "builtIn": 1,
        "datasource": { "type": "grafana", "uid": "-- Grafana --" },
        "enable": true,
        "hide": true,
        "iconColor": "rgba(0, 211, 255, 1)",
        "name": "Annotations & Alerts",
        "type": "dashboard"
      }
    ]
  },
  "description": "Container and host system resources — CPU, memory, network I/O per container from cAdvisor and node-exporter",
  "editable": true,
  "fiscalYearStartMonth": 0,
  "graphTooltip": 1,
  "id": null,
  "links": [],
  "panels": [
    {
      "collapsed": false,
      "gridPos": { "h": 1, "w": 24, "x": 0, "y": 0 },
      "id": 100,
      "title": "Host Resources",
      "type": "row"
    },
    {
      "datasource": { "type": "prometheus", "uid": "prometheus" },
      "description": "Total host CPU utilization from node-exporter",
      "fieldConfig": {
        "defaults": {
          "color": { "mode": "palette-classic" },
          "custom": {
            "axisLabel": "CPU %",
            "drawStyle": "line",
            "fillOpacity": 15,
            "gradientMode": "opacity",
            "lineInterpolation": "smooth",
            "lineWidth": 2,
            "showPoints": "never",
            "spanNulls": false
          },
          "mappings": [],
          "max": 100,
          "min": 0,
          "thresholds": {
            "mode": "absolute",
            "steps": [
              { "color": "green", "value": null },
              { "color": "yellow", "value": 70 },
              { "color": "red", "value": 90 }
            ]
          },
          "unit": "percent"
        },
        "overrides": []
      },
      "gridPos": { "h": 8, "w": 12, "x": 0, "y": 1 },
      "id": 1,
      "options": {
        "legend": { "calcs": ["mean", "max", "lastNotNull"], "displayMode": "table", "placement": "bottom", "showLegend": true },
        "tooltip": { "mode": "multi", "sort": "desc" }
      },
      "targets": [
        {
          "datasource": { "type": "prometheus", "uid": "prometheus" },
          "editorMode": "code",
          "expr": "100 - (avg by (instance) (rate(node_cpu_seconds_total{mode=\"idle\"}[5m])) * 100)",
          "legendFormat": "Host CPU % ({{instance}})",
          "range": true,
          "refId": "A"
        },
        {
          "datasource": { "type": "prometheus", "uid": "prometheus" },
          "editorMode": "code",
          "expr": "avg by (instance) (rate(node_cpu_seconds_total{mode=\"iowait\"}[5m])) * 100",
          "legendFormat": "I/O Wait % ({{instance}})",
          "range": true,
          "refId": "B"
        }
      ],
      "title": "Host CPU Total",
      "type": "timeseries"
    },
    {
      "datasource": { "type": "prometheus", "uid": "prometheus" },
      "description": "Host memory available and total from node-exporter",
      "fieldConfig": {
        "defaults": {
          "color": { "mode": "palette-classic" },
          "custom": {
            "axisLabel": "bytes",
            "drawStyle": "line",
            "fillOpacity": 15,
            "gradientMode": "opacity",
            "lineInterpolation": "smooth",
            "lineWidth": 2,
            "showPoints": "never",
            "spanNulls": false
          },
          "mappings": [],
          "unit": "bytes"
        },
        "overrides": [
          { "matcher": { "id": "byName", "options": "Available" }, "properties": [{ "id": "color", "value": { "fixedColor": "green", "mode": "fixed" } }] },
          { "matcher": { "id": "byName", "options": "Total" }, "properties": [{ "id": "color", "value": { "fixedColor": "blue", "mode": "fixed" } }, { "id": "custom.lineStyle", "value": { "dash": [10, 10], "fill": "dash" } }] },
          { "matcher": { "id": "byName", "options": "Used" }, "properties": [{ "id": "color", "value": { "fixedColor": "orange", "mode": "fixed" } }] }
        ]
      },
      "gridPos": { "h": 8, "w": 12, "x": 12, "y": 1 },
      "id": 2,
      "options": {
        "legend": { "calcs": ["mean", "max", "lastNotNull"], "displayMode": "table", "placement": "bottom", "showLegend": true },
        "tooltip": { "mode": "multi", "sort": "desc" }
      },
      "targets": [
        {
          "datasource": { "type": "prometheus", "uid": "prometheus" },
          "editorMode": "code",
          "expr": "node_memory_MemAvailable_bytes",
          "legendFormat": "Available",
          "range": true,
          "refId": "A"
        },
        {
          "datasource": { "type": "prometheus", "uid": "prometheus" },
          "editorMode": "code",
          "expr": "node_memory_MemTotal_bytes - node_memory_MemAvailable_bytes",
          "legendFormat": "Used",
          "range": true,
          "refId": "B"
        },
        {
          "datasource": { "type": "prometheus", "uid": "prometheus" },
          "editorMode": "code",
          "expr": "node_memory_MemTotal_bytes",
          "legendFormat": "Total",
          "range": true,
          "refId": "C"
        }
      ],
      "title": "Host Memory Available",
      "type": "timeseries"
    },
    {
      "collapsed": false,
      "gridPos": { "h": 1, "w": 24, "x": 0, "y": 9 },
      "id": 101,
      "title": "Container CPU",
      "type": "row"
    },
    {
      "datasource": { "type": "prometheus", "uid": "prometheus" },
      "description": "CPU usage per container from cAdvisor — rate of cpu_usage_seconds_total",
      "fieldConfig": {
        "defaults": {
          "color": { "mode": "palette-classic" },
          "custom": {
            "axisLabel": "CPU cores",
            "drawStyle": "line",
            "fillOpacity": 10,
            "gradientMode": "none",
            "lineInterpolation": "smooth",
            "lineWidth": 1,
            "showPoints": "never",
            "spanNulls": false
          },
          "mappings": [],
          "unit": "short"
        },
        "overrides": []
      },
      "gridPos": { "h": 9, "w": 24, "x": 0, "y": 10 },
      "id": 3,
      "options": {
        "legend": { "calcs": ["mean", "max", "lastNotNull"], "displayMode": "table", "placement": "right", "showLegend": true },
        "tooltip": { "mode": "multi", "sort": "desc" }
      },
      "targets": [
        {
          "datasource": { "type": "prometheus", "uid": "prometheus" },
          "editorMode": "code",
          "expr": "sum(rate(container_cpu_usage_seconds_total{name=~\"$container\", name!=\"\", image!=\"\"}[5m])) by (name)",
          "legendFormat": "{{name}}",
          "range": true,
          "refId": "A"
        }
      ],
      "title": "CPU Usage per Container",
      "type": "timeseries"
    },
    {
      "collapsed": false,
      "gridPos": { "h": 1, "w": 24, "x": 0, "y": 19 },
      "id": 102,
      "title": "Container Memory",
      "type": "row"
    },
    {
      "datasource": { "type": "prometheus", "uid": "prometheus" },
      "description": "Memory usage per container from cAdvisor",
      "fieldConfig": {
        "defaults": {
          "color": { "mode": "palette-classic" },
          "custom": {
            "axisLabel": "bytes",
            "drawStyle": "line",
            "fillOpacity": 10,
            "gradientMode": "none",
            "lineInterpolation": "smooth",
            "lineWidth": 1,
            "showPoints": "never",
            "spanNulls": false
          },
          "mappings": [],
          "unit": "bytes"
        },
        "overrides": []
      },
      "gridPos": { "h": 9, "w": 24, "x": 0, "y": 20 },
      "id": 4,
      "options": {
        "legend": { "calcs": ["mean", "max", "lastNotNull"], "displayMode": "table", "placement": "right", "showLegend": true },
        "tooltip": { "mode": "multi", "sort": "desc" }
      },
      "targets": [
        {
          "datasource": { "type": "prometheus", "uid": "prometheus" },
          "editorMode": "code",
          "expr": "container_memory_usage_bytes{name=~\"$container\", name!=\"\", image!=\"\"}",
          "legendFormat": "{{name}}",
          "range": true,
          "refId": "A"
        }
      ],
      "title": "Memory Usage per Container",
      "type": "timeseries"
    },
    {
      "collapsed": false,
      "gridPos": { "h": 1, "w": 24, "x": 0, "y": 29 },
      "id": 103,
      "title": "Network I/O",
      "type": "row"
    },
    {
      "datasource": { "type": "prometheus", "uid": "prometheus" },
      "description": "Network receive and transmit bytes per second per container",
      "fieldConfig": {
        "defaults": {
          "color": { "mode": "palette-classic" },
          "custom": {
            "axisLabel": "bytes/s",
            "drawStyle": "line",
            "fillOpacity": 8,
            "gradientMode": "none",
            "lineInterpolation": "smooth",
            "lineWidth": 1,
            "showPoints": "never",
            "spanNulls": false
          },
          "mappings": [],
          "unit": "Bps"
        },
        "overrides": []
      },
      "gridPos": { "h": 9, "w": 24, "x": 0, "y": 30 },
      "id": 5,
      "options": {
        "legend": { "calcs": ["mean", "max", "lastNotNull"], "displayMode": "table", "placement": "right", "showLegend": true },
        "tooltip": { "mode": "multi", "sort": "desc" }
      },
      "targets": [
        {
          "datasource": { "type": "prometheus", "uid": "prometheus" },
          "editorMode": "code",
          "expr": "sum(rate(container_network_receive_bytes_total{name=~\"$container\", name!=\"\"}[5m])) by (name)",
          "legendFormat": "RX {{name}}",
          "range": true,
          "refId": "A"
        },
        {
          "datasource": { "type": "prometheus", "uid": "prometheus" },
          "editorMode": "code",
          "expr": "-sum(rate(container_network_transmit_bytes_total{name=~\"$container\", name!=\"\"}[5m])) by (name)",
          "legendFormat": "TX {{name}} (neg)",
          "range": true,
          "refId": "B"
        }
      ],
      "title": "Network I/O per Container (RX / TX)",
      "type": "timeseries"
    }
  ],
  "refresh": "10s",
  "schemaVersion": 38,
  "tags": ["system", "containers", "cadvisor", "node-exporter", "infervoyage"],
  "templating": {
    "list": [
      {
        "current": { "selected": false, "text": "All", "value": "$__all" },
        "datasource": { "type": "prometheus", "uid": "prometheus" },
        "definition": "label_values(container_cpu_usage_seconds_total{image!=\"\"}, name)",
        "hide": 0,
        "includeAll": true,
        "label": "Container",
        "multi": true,
        "name": "container",
        "options": [],
        "query": {
          "qryType": 1,
          "query": "label_values(container_cpu_usage_seconds_total{image!=\"\"}, name)",
          "refId": "StandardVariableQuery"
        },
        "refresh": 2,
        "regex": "",
        "skipUrlSync": false,
        "sort": 1,
        "type": "query"
      }
    ]
  },
  "time": { "from": "now-1h", "to": "now" },
  "timepicker": {},
  "timezone": "browser",
  "title": "System Overview",
  "uid": "system-overview",
  "version": 1,
  "weekStart": ""
}
